{
  "$schema": "https://mintlify.com/docs.json",
  "name": "Zendriver",
  "theme": "aspen",
  "colors": {
    "primary": "#6366f1",
    "light": "#818cf8",
    "dark": "#4f46e5"
  },
  "navbar": {
    "primary": {
      "type": "github",
      "href": "https://github.com/cdpdriver/zendriver"
    }
  },
  "footer": {
    "socials": {
      "github": "https://github.com/cdpdriver/zendriver"
    }
  },
  "navigation": {
    "tabs": [
      {
        "tab": "Documentation",
        "groups": [
          {
            "group": "Get Started",
            "pages": [
              "introduction",
              "quickstart",
              "installation"
            ]
          },
          {
            "group": "Core Concepts",
            "pages": [
              "concepts/browser",
              "concepts/tabs",
              "concepts/elements",
              "concepts/configuration"
            ]
          },
          {
            "group": "Guides",
            "pages": [
              "guides/basic-scraping",
              "guides/element-interaction",
              "guides/waiting-and-timing",
              "guides/screenshots-and-pdfs",
              "guides/cookies-and-sessions",
              "guides/network-monitoring",
              "guides/keyboard-and-mouse"
            ]
          },
          {
            "group": "Advanced",
            "pages": [
              "advanced/cdp-commands",
              "advanced/request-interception",
              "advanced/cloudflare-bypass",
              "advanced/docker-deployment",
              "advanced/anti-detection"
            ]
          },
          {
            "group": "Tutorials",
            "pages": [
              "tutorials/account-creation",
              "tutorials/infinite-scrolling",
              "tutorials/api-responses"
            ]
          },
          {
            "group": "Examples",
            "pages": [
              "examples/browserscan",
              "examples/imgur-upload",
              "examples/network-monitor",
              "examples/file-download"
            ]
          }
        ]
      },
      {
        "tab": "API Reference",
        "groups": [
          {
            "group": "Core API",
            "pages": [
              "api/start",
              "api/browser",
              "api/tab",
              "api/element",
              "api/config"
            ]
          },
          {
            "group": "Input & Interaction",
            "pages": [
              "api/keys",
              "api/mouse"
            ]
          },
          {
            "group": "Advanced",
            "pages": [
              "api/connection",
              "api/cdp",
              "api/expect",
              "api/intercept"
            ]
          }
        ]
      }
    ]
  }
}
